folder_manager/__init__.py
folder_manager/folder_manager.py
folder_manager-1.1.0.dist-info/METADATA
folder_manager-1.1.0.dist-info/WHEEL
folder_manager-1.1.0.dist-info/top_level.txt
folder_manager-1.1.0.dist-info/RECORD
