Metadata-Version: 2.1
Name: folder_manager
Version: 1.1.0
Summary: A simple folder management library designed to manage folders and files. It provides functionalities to create, list, count, and delete files and folders, making it a versatile tool for file management. The package is designed to be OS-independent, ensuring compatibility with both Windows and Unix-based systems.
Home-page: https://github.com/phintegrator/folder_manager
Author: Javer Valino
Classifier: Programming Language :: Python :: 3
Classifier: License :: OSI Approved :: MIT License
Classifier: Operating System :: OS Independent
Requires-Python: >=3.6
